omero_fpbioimage/__init__.py
omero_fpbioimage/apps.py
omero_fpbioimage/urls.py
omero_fpbioimage/utils.py
omero_fpbioimage/version.py
omero_fpbioimage/views.py
omero_fpbioimage/__pycache__/__init__.cpython-310.pyc
omero_fpbioimage/__pycache__/utils.cpython-310.pyc
omero_fpbioimage/__pycache__/version.cpython-310.pyc
omero_fpbioimage/static/fpbioimage/openwith.js
omero_fpbioimage/static/fpbioimage/FPBioimage/FPBioimage.asm.code.unityweb
omero_fpbioimage/static/fpbioimage/FPBioimage/FPBioimage.asm.framework.unityweb
omero_fpbioimage/static/fpbioimage/FPBioimage/FPBioimage.asm.memory.unityweb
omero_fpbioimage/static/fpbioimage/FPBioimage/FPBioimage.data.unityweb
omero_fpbioimage/static/fpbioimage/FPBioimage/FPBioimage.json
omero_fpbioimage/static/fpbioimage/FPBioimage/FPLoader.js
omero_fpbioimage/static/fpbioimage/FPBioimage/FPProgress.js
omero_fpbioimage/static/fpbioimage/FPBioimage/UnityLoader.js
omero_fpbioimage/static/fpbioimage/FPBioimage/download.js
omero_fpbioimage/static/fpbioimage/FPBioimage/empty.png
omero_fpbioimage/static/fpbioimage/FPBioimage/full.png
omero_fpbioimage/static/fpbioimage/FPBioimage/logo.png
omero_fpbioimage/static/fpbioimage/resources/LAGlogo.png
omero_fpbioimage/static/fpbioimage/resources/cambridgeLogo.png
omero_fpbioimage/static/fpbioimage/resources/fullscreen.png
omero_fpbioimage/templates/fpbioimage/viewer.html
omero_fpbioimage-0.4.1.dist-info/METADATA
omero_fpbioimage-0.4.1.dist-info/WHEEL
omero_fpbioimage-0.4.1.dist-info/top_level.txt
omero_fpbioimage-0.4.1.dist-info/RECORD
